ragrid/__init__.py
ragrid/document_extractor.py
ragrid/evaluation_question_generator.py
ragrid/evalutation.py
ragrid/hub.py
ragrid/library_exceptions.py
ragrid/text_chunker.py
ragrid/text_cleaner.py
ragrid/text_embeddings.py
ragrid/text_utils.py
ragrid/tru_lens_evaluator.py
ragrid-0.1.4.dist-info/LICENSE
ragrid-0.1.4.dist-info/METADATA
ragrid-0.1.4.dist-info/WHEEL
ragrid-0.1.4.dist-info/top_level.txt
ragrid-0.1.4.dist-info/RECORD
