Metadata-Version: 2.1
Name: ragrid
Version: 0.1.4
Summary: This library is to search the best parameters across different steps of the RAG process.
Home-page: https://github.com/hidevscommunity/ragrid
Author: HiDevs
Author-email: hidevscommunity@gmail.com
License: MIT
Classifier: License :: OSI Approved :: MIT License
Classifier: Programming Language :: Python :: 3.9
Classifier: Programming Language :: Python :: 3.10
Classifier: Programming Language :: Python :: 3.11
License-File: LICENSE
Requires-Dist: langchain >=0.1.13
Requires-Dist: langchain-openai >=0.1.1
Requires-Dist: trulens-eval >=0.27.0
Requires-Dist: chromadb >=0.4.24
Requires-Dist: sentence-transformers >=2.6.1
Requires-Dist: unstructured[pdf] >=0.13.0
Requires-Dist: deepeval >=0.21.71
Requires-Dist: faiss-cpu >=1.8.0.post1
Requires-Dist: langchainhub >=0.1.20
